oasvalidator.cpython-38-x86_64-linux-gnu.so
oasvalidator-1.0.0.dist-info/RECORD
oasvalidator-1.0.0.dist-info/WHEEL
oasvalidator-1.0.0.dist-info/LICENSE
oasvalidator-1.0.0.dist-info/METADATA
oasvalidator-1.0.0.dist-info/top_level.txt
